ilo_scripting_helper/__init__.py
ilo_scripting_helper/_version.py
ilo_scripting_helper/ilo_scripting_helper.py
ilo_scripting_helper-0.0.2.dist-info/LICENSE
ilo_scripting_helper-0.0.2.dist-info/METADATA
ilo_scripting_helper-0.0.2.dist-info/WHEEL
ilo_scripting_helper-0.0.2.dist-info/top_level.txt
ilo_scripting_helper-0.0.2.dist-info/RECORD
