Metadata-Version: 2.1
Name: ilo-scripting-helper
Version: 0.0.2
Summary: A Python library to provide useful function for scripting for iLO
Author: Muhammad Balagamwala
Author-email: muhammadb@hpe.com
Classifier: Programming Language :: Python :: 3
Classifier: License :: OSI Approved :: GNU General Public License (GPL)
Classifier: Operating System :: OS Independent
Requires-Python: >=3.6
License-File: LICENSE
Requires-Dist: requests (==2.27.1)
